liz_mymcp/__init__.py
liz_mymcp-0.1.0.dist-info/METADATA
liz_mymcp-0.1.0.dist-info/WHEEL
liz_mymcp-0.1.0.dist-info/entry_points.txt
liz_mymcp-0.1.0.dist-info/RECORD
